flatpak_pip_generator/__main__.py
flatpak_pip_generator-25.0.0.dist-info/METADATA
flatpak_pip_generator-25.0.0.dist-info/WHEEL
flatpak_pip_generator-25.0.0.dist-info/entry_points.txt
flatpak_pip_generator-25.0.0.dist-info/top_level.txt
flatpak_pip_generator-25.0.0.dist-info/RECORD
