Metadata-Version: 2.4
Name: flatpak_pip_generator
Version: 25.0.0
Summary: this is an unofficial pypi distribution of the flatpak_pip_generator script
Project-URL: upstream, https://github.com/flatpak/flatpak-builder-tools/tree/master/pip
Project-URL: downstream, https://github.com/gmanka-flatpaks/flatpak_pip_generator
Classifier: License :: OSI Approved :: MIT License
Requires-Dist: requirements-parser
Requires-Dist: pyyaml
Provides-Extra: build
Requires-Dist: setuptools; extra == "build"
Requires-Dist: twine; extra == "build"
Requires-Dist: build; extra == "build"
